inventree_lectronz/__init__.py
inventree_lectronz/create_sales_order.py
inventree_lectronz/lectronz_v1.py
inventree_lectronz/plugin.py
inventree_lectronz/templatetags.py
inventree_lectronz/templates/lectronz_order.html
inventree_lectronz/templates/lectronz_product.html
inventree_lectronz-1.1.dist-info/METADATA
inventree_lectronz-1.1.dist-info/WHEEL
inventree_lectronz-1.1.dist-info/entry_points.txt
inventree_lectronz-1.1.dist-info/licenses/LICENSE
inventree_lectronz-1.1.dist-info/RECORD
