Metadata-Version: 2.4
Name: inventree-lectronz
Version: 1.1
Summary: Lectronz integration for InvenTree
Project-URL: Homepage, https://github.com/30350n/inventree_lectronz
Author-email: Bobbe <mail@30350n.de>
License: MIT
License-File: LICENSE
Keywords: inventree,inventree-lectronz,inventree-plugin,lectronz
Classifier: Development Status :: 5 - Production/Stable
Classifier: Environment :: Plugins
Classifier: License :: OSI Approved :: MIT License
Classifier: Programming Language :: Python :: 3
Requires-Python: >=3.8
